.gitignore
README.txt
setup.py
docs/CHANGES.txt
docs/CONTRIBUTORS.txt
docs/LICENSE.GPL
docs/LICENSE.txt
src/collective/__init__.py
src/collective.memberemails.egg-info/PKG-INFO
src/collective.memberemails.egg-info/SOURCES.txt
src/collective.memberemails.egg-info/dependency_links.txt
src/collective.memberemails.egg-info/entry_points.txt
src/collective.memberemails.egg-info/namespace_packages.txt
src/collective.memberemails.egg-info/not-zip-safe
src/collective.memberemails.egg-info/requires.txt
src/collective.memberemails.egg-info/top_level.txt
src/collective/memberemails/__init__.py
src/collective/memberemails/configure.zcml
src/collective/memberemails/controlpanel.py
src/collective/memberemails/handlers.py
src/collective/memberemails/interfaces.py
src/collective/memberemails/testing.py
src/collective/memberemails/profiles/default/controlpanel.xml
src/collective/memberemails/profiles/default/metadata.xml
src/collective/memberemails/profiles/default/registry.xml
src/collective/memberemails/tests/__init__.py
src/collective/memberemails/tests/test_approval.py
src/collective/memberemails/tests/test_installed.py